LICENSE
MANIFEST.in
README.rst
setup.py
flask_redis_log.egg-info/PKG-INFO
flask_redis_log.egg-info/SOURCES.txt
flask_redis_log.egg-info/dependency_links.txt
flask_redis_log.egg-info/requires.txt
flask_redis_log.egg-info/top_level.txt
redislogs/__init__.py
redislogs/formatters.py
redislogs/handlers.py