Metadata-Version: 1.0
Name: flask-redis-log
Version: 0.0.1
Summary: Redis pub/sub logging handler for python
Home-page: https://gitlab.wearegap.com/lcordero/flask-redis-logs.git
Author: Luis Diego Cordero
Author-email: ldiego@gmail.com
License: MIT
Platform: UNKNOWN
